backtester/__init__.py
backtester/backtest/__init__.py
backtester/backtest/backtest.py
backtester/metrics/__init__.py
backtester/metrics/func_names.py
backtester/metrics/metrics.py
backtester-0.7.dist-info/LICENSE
backtester-0.7.dist-info/METADATA
backtester-0.7.dist-info/WHEEL
backtester-0.7.dist-info/top_level.txt
backtester-0.7.dist-info/RECORD
