Metadata-Version: 2.1
Name: backtester
Version: 0.7
Summary: A backtesting for timeseries data in a pandas dataframe
Home-page: https://github.com/EricSchles/backtester
Author: Eric Schles
Author-email: ericschles@gmail.com
License: MIT
Platform: UNKNOWN
Classifier: License :: OSI Approved :: MIT License
Classifier: Programming Language :: Python :: 3
Classifier: Programming Language :: Python :: 3.6
Classifier: Programming Language :: Python :: 3.7
Requires-Dist: sklearn
Requires-Dist: scipy
Requires-Dist: numpy
Requires-Dist: empiricaldist
Requires-Dist: statsmodels
Requires-Dist: mlxtend
Requires-Dist: pytest
